flake8_efm.py
flake8_efm-1.0.2.dist-info/LICENCE
flake8_efm-1.0.2.dist-info/METADATA
flake8_efm-1.0.2.dist-info/WHEEL
flake8_efm-1.0.2.dist-info/entry_points.txt
flake8_efm-1.0.2.dist-info/top_level.txt
flake8_efm-1.0.2.dist-info/RECORD
