Metadata-Version: 2.1
Name: flake8-efm
Version: 1.0.2
Summary: Plugin for EFM-compatible output.
Home-page: https://git.sr.ht/~whynothugo/flake8-efm
Author: Hugo Osvaldo Barrera
Author-email: hugo@barrera.io
License: ISC
Platform: UNKNOWN
Classifier: Environment :: Console
Classifier: Framework :: Flake8
Classifier: Intended Audience :: Developers
Classifier: License :: OSI Approved :: ISC License (ISCL)
Classifier: Programming Language :: Python :: 3
Classifier: Programming Language :: Python
Classifier: Topic :: Software Development :: Libraries :: Python Modules
Classifier: Topic :: Software Development :: Quality Assurance
Requires-Dist: flake8 (>3.0.0)
